{"Player1Move":{"SuccessfulMove":true,"CommandIssued":"FireSingleShot","CenterPoint":"3, 5","ShieldRadius":2,"PlaceShipString":"Carrier 8 8 south ,Battleship 0 0 north ,Submarine 1 8 east ,Cruiser 9 0 north ,Destroyer 5 5 east ","Energy":21,"RemainingShieldTurns":6},"Player2Move":{"SuccessfulMove":true,"CommandIssued":"FireSingleShot","CenterPoint":"1, 7","ShieldRadius":2,"PlaceShipString":"Battleship 1 1 north ,Carrier 4 1 East ,Cruiser 4 4 north ,Destroyer 7 6 north ,Submarine 1 8 East ","Energy":35,"RemainingShieldTurns":6}}